.bumpversion.cfg
.editorconfig
.gitignore
CODE_OF_CONDUCT.md
LICENSE.txt
MANIFEST.in
Makefile
README.md
setup.py
csvlexer/__init__.py
csvlexer/__version__.py
csvlexer/csv.py
pygments_csv_lexer.egg-info/PKG-INFO
pygments_csv_lexer.egg-info/SOURCES.txt
pygments_csv_lexer.egg-info/dependency_links.txt
pygments_csv_lexer.egg-info/entry_points.txt
pygments_csv_lexer.egg-info/requires.txt
pygments_csv_lexer.egg-info/top_level.txt
pygments_csv_lexer.egg-info/zip-safe
requirements/dev.txt
requirements/install.txt