Metadata-Version: 2.1
Name: pygments-csv-lexer
Version: 0.1.2
Summary:  Install custom csv lexer
